ratemaking_tools/__init__.py
ratemaking_tools/complements/__init__.py
ratemaking_tools/complements/first_dollar.py
ratemaking_tools/credibility/__init__.py
ratemaking_tools/credibility/bayesian.py
ratemaking_tools/credibility/buhlmann.py
ratemaking_tools/credibility/classical.py
ratemaking_tools/exposure/__init__.py
ratemaking_tools/exposure/calculations.py
ratemaking_tools/trending/__init__.py
ratemaking_tools/trending/trend_analysis.py
ratemaking_tools/utils/__init__.py
ratemaking_tools/utils/data_processing.py
ratemaking_tools-0.3.0.dist-info/licenses/LICENSE
tests/__init__.py
tests/test_complements.py
tests/test_credibility.py
ratemaking_tools-0.3.0.dist-info/METADATA
ratemaking_tools-0.3.0.dist-info/WHEEL
ratemaking_tools-0.3.0.dist-info/top_level.txt
ratemaking_tools-0.3.0.dist-info/RECORD
