Metadata-Version: 2.4
Name: ratemaking-tools
Version: 0.3.0
Summary: A comprehensive Python library for P&C actuarial ratemaking
Home-page: https://github.com/little-croissant/ratemaking-tools
Author: Aria Team
Author-email: your-email@example.com
Project-URL: Bug Reports, https://github.com/little-croissant/ratemaking-tools/issues
Project-URL: Source, https://github.com/little-croissant/ratemaking-tools
Project-URL: Documentation, https://github.com/little-croissant/ratemaking-tools#readme
Keywords: actuarial ratemaking credibility complements insurance P&C casualty property
Classifier: Development Status :: 3 - Alpha
Classifier: Intended Audience :: Financial and Insurance Industry
Classifier: Topic :: Office/Business :: Financial
Classifier: Topic :: Scientific/Engineering :: Mathematics
Classifier: License :: OSI Approved :: MIT License
Classifier: Operating System :: OS Independent
Classifier: Programming Language :: Python :: 3
Classifier: Programming Language :: Python :: 3.8
Classifier: Programming Language :: Python :: 3.9
Classifier: Programming Language :: Python :: 3.10
Classifier: Programming Language :: Python :: 3.11
Classifier: Programming Language :: Python :: 3.12
Requires-Python: >=3.8
License-File: LICENSE
Requires-Dist: pandas>=1.3.0
Provides-Extra: test
Requires-Dist: pytest>=7.0.0; extra == "test"
Requires-Dist: numpy>=1.20.0; extra == "test"
Requires-Dist: pandas>=1.3.0; extra == "test"
Requires-Dist: pyperclip>=1.8.0; extra == "test"
Requires-Dist: pyautogui>=0.9.0; extra == "test"
Requires-Dist: watchdog>=2.0.0; extra == "test"
Provides-Extra: dev
Requires-Dist: pytest>=7.0.0; extra == "dev"
Requires-Dist: black; extra == "dev"
Requires-Dist: flake8; extra == "dev"
Requires-Dist: mypy; extra == "dev"
Dynamic: author
Dynamic: author-email
Dynamic: classifier
Dynamic: description
Dynamic: description-content-type
Dynamic: home-page
Dynamic: keywords
Dynamic: license-file
Dynamic: project-url
Dynamic: provides-extra
Dynamic: requires-dist
Dynamic: requires-python
Dynamic: summary
